tldap/__init__.py
tldap/backend/__init__.py
tldap/backend/base.py
tldap/backend/fake_transactions.py
tldap/backend/no_transactions.py
tldap/database/__init__.py
tldap/database/helpers.py
tldap/dict.py
tldap/django/__init__.py
tldap/django/apps.py
tldap/django/helpers.py
tldap/django/middleware.py
tldap/django/migrations/0001_initial.py
tldap/django/migrations/__init__.py
tldap/django/models.py
tldap/dn.py
tldap/exceptions.py
tldap/fields.py
tldap/filter.py
tldap/ldap_passwd.py
tldap/modlist.py
tldap/query.py
tldap/query_utils.py
tldap/test/__init__.py
tldap/test/ldap_schemas/00-core.schema
tldap/test/ldap_schemas/10-cosine.schema
tldap/test/ldap_schemas/50-inetorgperson.schema
tldap/test/ldap_schemas/70-eduperson.schema
tldap/test/ldap_schemas/90-aueduperson.schema
tldap/test/ldap_schemas/90-schac.schema
tldap/test/ldap_schemas/nis.schema
tldap/test/slapd.py
tldap/transaction.py
tldap/tree.py
tldap/utils.py
python_tldap-1.0.8.dist-info/COPYING.txt
python_tldap-1.0.8.dist-info/WHEEL
python_tldap-1.0.8.dist-info/METADATA
python_tldap-1.0.8.dist-info/RECORD
